discode.py
discode-0.0.9.dist-info/DESCRIPTION.rst
discode-0.0.9.dist-info/METADATA
discode-0.0.9.dist-info/RECORD
discode-0.0.9.dist-info/WHEEL
discode-0.0.9.dist-info/entry_points.txt
discode-0.0.9.dist-info/metadata.json
discode-0.0.9.dist-info/top_level.txt
