Metadata-Version: 2.0
Name: discode
Version: 0.0.9
Summary: Quick code review
Home-page: https://github.com/d0ugal/discode
Author: Dougal Matthews
Author-email: dougal@dougalmatthews.com
License: BSD
Keywords: code review codereview discussion
Platform: UNKNOWN
